examples/__init__.py
examples/logger.py
examples/miner.py
examples/pool.py
examples/run.py
examples/wallet.py
examples/common/__init__.py
examples/common/conf.py
examples/common/utils.py
examples/listener/__init__.py
examples/listener/logger.py
examples/listener/miner.py
examples/listener/pool.py
openchain/__init__.py
openchain/adapters/__init__.py
openchain/adapters/base.py
openchain/adapters/leveldb.py
openchain/adapters/plyvel.py
openchain/models/__init__.py
openchain/models/base.py
openchain/models/block.py
openchain/models/blockchain.py
openchain/models/client.py
openchain/models/database.py
openchain/models/exception.py
openchain/models/exceptions.py
openchain/models/factory.py
openchain/models/logentry.py
openchain/models/transaction.py
openchain/models/wallet.py
openchain/utils/__init__.py
openchain/utils/base.py
openchain/utils/network.py
openchain/utils/stun.py
openchain-0.1.0rc3.dist-info/LICENSE.txt
openchain-0.1.0rc3.dist-info/METADATA
openchain-0.1.0rc3.dist-info/WHEEL
openchain-0.1.0rc3.dist-info/top_level.txt
openchain-0.1.0rc3.dist-info/RECORD
