Metadata-Version: 2.1
Name: openchain
Version: 0.1.0rc3
Summary: Openchain Library
Home-page: https://bitbucket.org/manti_by/openchain/
Author: Alexander Chaika
Author-email: manti.by@gmail.com
License: BSD
Keywords: blockchain
Platform: UNKNOWN
Classifier: Development Status :: 4 - Beta
Classifier: Intended Audience :: Developers
Classifier: Topic :: Software Development :: Libraries :: Python Modules
Classifier: License :: OSI Approved :: BSD License
Classifier: Programming Language :: Python :: 3.6
Classifier: Operating System :: POSIX :: Linux
Requires-Python: >=3.6
Requires-Dist: ecdsa (<0.14leveldb>=0.194,<0.195,>=0.13)
Requires-Dist: plyvel (<1.1.0,>=1.0.5)
Requires-Dist: xxhash (<1.3.0,>=1.2.0)
